gupi/__init__.py
gupi/cli.py
gupi/common.py
gupi/custom_logger.py
gupi/error_handler.py
gupi/errors.py
tools/__init__.py
tools/analyser/__init__.py
tools/analyser/main.py
tools/runner/__init__.py
tools/runner/main.py
gupi-1.0.9.dist-info/LICENSE
gupi-1.0.9.dist-info/METADATA
gupi-1.0.9.dist-info/WHEEL
gupi-1.0.9.dist-info/entry_points.txt
gupi-1.0.9.dist-info/top_level.txt
gupi-1.0.9.dist-info/RECORD
